Metadata-Version: 1.0
Name: easy-datatable
Version: 0.1
Summary: print data as a table or change data alignment
Home-page: UNKNOWN
Author: TheNightmare
Author-email: 2553036363@qq.com
License: UNKNOWN
Platform: UNKNOWN
